langsmith_pyo3-0.1.0rc5.dist-info/METADATA
langsmith_pyo3-0.1.0rc5.dist-info/WHEEL
langsmith_pyo3/__init__.py
langsmith_pyo3/langsmith_pyo3.cpython-313-x86_64-linux-gnu.so
langsmith_pyo3-0.1.0rc5.dist-info/RECORD
