Metadata-Version: 2.4
Name: langsmith-pyo3
Version: 0.1.0rc5
Classifier: Programming Language :: Rust
Classifier: Programming Language :: Python :: Implementation :: CPython
Classifier: Programming Language :: Python :: Implementation :: PyPy
Requires-Python: >=3.9
